pyaffalddk/__init__.py
pyaffalddk/api.py
pyaffalddk/const.py
pyaffalddk/data.py
pyaffalddk/images.py
pyaffalddk/interface.py
pyaffalddk/municipalities.py
pyaffalddk/supported_items.json
pyaffalddk-2.13.1.dist-info/licenses/LICENSE
tests/__init__.py
tests/test_api.py
tests/test_interface.py
pyaffalddk-2.13.1.dist-info/METADATA
pyaffalddk-2.13.1.dist-info/WHEEL
pyaffalddk-2.13.1.dist-info/top_level.txt
pyaffalddk-2.13.1.dist-info/RECORD
