Metadata-Version: 2.4
Name: pyaffalddk
Version: 2.13.1
Summary: Gets garbage collection data from danish Municipalities
Home-page: https://github.com/briis/pyaffalddk
Author: briis
Author-email: bjarne@briis.com
License: MIT
Classifier: Programming Language :: Python :: 3
Classifier: License :: OSI Approved :: MIT License
Classifier: Operating System :: OS Independent
Classifier: Development Status :: 4 - Beta
License-File: LICENSE
Dynamic: author
Dynamic: author-email
Dynamic: classifier
Dynamic: description
Dynamic: description-content-type
Dynamic: home-page
Dynamic: license
Dynamic: license-file
Dynamic: summary
